odoo/addons/account_fiscal_position_allowed_journal_sale_purchase/README.rst
odoo/addons/account_fiscal_position_allowed_journal_sale_purchase/__init__.py
odoo/addons/account_fiscal_position_allowed_journal_sale_purchase/__manifest__.py
odoo/addons/account_fiscal_position_allowed_journal_sale_purchase/i18n/account_fiscal_position_allowed_journal_sale_purchase.pot
odoo/addons/account_fiscal_position_allowed_journal_sale_purchase/models/__init__.py
odoo/addons/account_fiscal_position_allowed_journal_sale_purchase/models/account_move.py
odoo/addons/account_fiscal_position_allowed_journal_sale_purchase/readme/CONFIGURE.rst
odoo/addons/account_fiscal_position_allowed_journal_sale_purchase/readme/CONTRIBUTORS.rst
odoo/addons/account_fiscal_position_allowed_journal_sale_purchase/readme/DESCRIPTION.rst
odoo/addons/account_fiscal_position_allowed_journal_sale_purchase/static/description/icon.png
odoo/addons/account_fiscal_position_allowed_journal_sale_purchase/static/description/index.html
odoo/addons/account_fiscal_position_allowed_journal_sale_purchase/tests/__init__.py
odoo/addons/account_fiscal_position_allowed_journal_sale_purchase/tests/test_account_fiscal_position_allowed_journal_purchase.py
odoo13_addon_account_fiscal_position_allowed_journal_sale_purchase-13.0.1.0.1.dev2.dist-info/METADATA
odoo13_addon_account_fiscal_position_allowed_journal_sale_purchase-13.0.1.0.1.dev2.dist-info/WHEEL
odoo13_addon_account_fiscal_position_allowed_journal_sale_purchase-13.0.1.0.1.dev2.dist-info/top_level.txt
odoo13_addon_account_fiscal_position_allowed_journal_sale_purchase-13.0.1.0.1.dev2.dist-info/RECORD
